setup.cfg
setup.py
django_dynamicstatics.egg-info/PKG-INFO
django_dynamicstatics.egg-info/SOURCES.txt
django_dynamicstatics.egg-info/dependency_links.txt
django_dynamicstatics.egg-info/requires.txt
django_dynamicstatics.egg-info/top_level.txt
dynamicstatics/__init__.py
dynamicstatics/templatetags/__init__.py
dynamicstatics/templatetags/media_url.py
dynamicstatics/templatetags/static_url.py