Metadata-Version: 1.1
Name: django-dynamicstatics
Version: 1.0.1
Summary: A Django utility application that dynamically changes MEDIA_URL and STATIC_URL
Home-page: https://github.com/kneufeld/django-dynamicstatics
Author: Kurt Neufeld
Author-email: kneufeld@burgundywall.com
License: MIT
Keywords: django,media_url,static_url
Platform: UNKNOWN
Classifier: Development Status :: 5 - Production/Stable
Classifier: Environment :: Web Environment
Classifier: Intended Audience :: Developers
Classifier: License :: OSI Approved :: MIT License
Classifier: Operating System :: OS Independent
Classifier: Programming Language :: Python
Classifier: Topic :: Utilities
